authenticator/__init__.py
authenticator/dataflowairflowauthenticator.py
authenticator/dataflowhubauthenticator.py
authenticator/package/__init__.py
authenticator/package/configuration.py
authenticator/package/models/__init__.py
authenticator/package/models/database.py
authenticator/package/models/session.py
authenticator/package/models/user.py
dataflow_authenticator-1.0.0.dist-info/METADATA
dataflow_authenticator-1.0.0.dist-info/WHEEL
dataflow_authenticator-1.0.0.dist-info/entry_points.txt
dataflow_authenticator-1.0.0.dist-info/top_level.txt
dataflow_authenticator-1.0.0.dist-info/RECORD
