Metadata-Version: 2.1
Name: dataflow-authenticator
Version: 1.0.0
Summary: Dataflow authenticator
Home-page: UNKNOWN
Author: Dataflow
Author-email: UNKNOWN
License: UNKNOWN
Platform: UNKNOWN
